coopgt/__init__.py
coopgt/characteristic_function_properties.py
coopgt/shapley_value.py
coopgt-0.0.2.dist-info/LICENSE
coopgt-0.0.2.dist-info/WHEEL
coopgt-0.0.2.dist-info/METADATA
coopgt-0.0.2.dist-info/RECORD
