Metadata-Version: 2.1
Name: coopgt
Version: 0.0.2
Summary: A library for the study of cooperative game theory.
Author: Vincent Knight
Author-email: knightva@cardiff.ac.uk
Requires-Python: >=3.10
Classifier: License :: OSI Approved :: MIT License
Requires-Dist: more-itertools >= 10.2.0
Requires-Dist: numpy >= 1.26.1
Requires-Dist: sphinx ; extra == "doc"
Requires-Dist: sphinx-rtd-theme ; extra == "doc"
Requires-Dist: sphinx-togglebutton ; extra == "doc"
Provides-Extra: doc
